vrs_clients/__init__.py
vrs_clients/models.py
vrs_clients/utils.py
vrs_clients/vrs_clients.py
vrs_clients-2.2.2.dist-info/LICENSE.txt
vrs_clients-2.2.2.dist-info/METADATA
vrs_clients-2.2.2.dist-info/WHEEL
vrs_clients-2.2.2.dist-info/top_level.txt
vrs_clients-2.2.2.dist-info/RECORD
